visualml/__init__.py
visualml/test_visual_ml.py
visualml/visualml.py
visualml-0.1b7.dist-info/DESCRIPTION.rst
visualml-0.1b7.dist-info/METADATA
visualml-0.1b7.dist-info/RECORD
visualml-0.1b7.dist-info/WHEEL
visualml-0.1b7.dist-info/metadata.json
visualml-0.1b7.dist-info/top_level.txt
