Metadata-Version: 2.0
Name: visualml
Version: 0.1b7
Summary: VisualML: Visualization of Multi-Dimensional Machine Learning Models
Home-page: https://github.com/wittmannf/visual-ml/
Author: Fernando Marcos Wittmann
Author-email: fernando.wittmann@gmail.com
License: BSD-4-Clause
Keywords: visualml
Platform: UNKNOWN
Classifier: Development Status :: 4 - Beta
Classifier: Intended Audience :: Science/Research
Classifier: License :: OSI Approved :: BSD License
Classifier: Natural Language :: English
Classifier: Programming Language :: Python :: 2
Classifier: Programming Language :: Python :: 2.7
Classifier: Programming Language :: Python :: 3
Classifier: Programming Language :: Python :: 3.4
Classifier: Programming Language :: Python :: 3.5
Classifier: Programming Language :: Python :: 3.6
